{"data":[{"parent":"idWarea","id":"div_0","tagName":"div","textContent":" ","attachClassName":[],"cssClassName":["pageWidth","pageHeight","mainContainer"],"css":[[[["width","80%"]],[["margin","0 auto"]],[["border","1px solid #aaa"]]],[[["height","100vh"]]],[[["position","relative"]]]],"js":{"functionName":[],"functionBlock":[]},"mediaQuery":{"cssClassName":[],"css":[]}},{"parent":"div_0","id":"header_1","tagName":"header","textContent":" ","attachClassName":[],"cssClassName":["headerContainer"],"css":[[[["height","300px"]],[["border","1px solid #aaa"]]]],"js":{"functionName":[],"functionBlock":[]},"mediaQuery":{"cssClassName":[],"css":[]}},{"parent":"header_1","id":"p_3","tagName":"p","textContent":"header","attachClassName":[],"cssClassName":["headerFontSize","headerColor"],"css":[[[["font-size","64px"]],[["text-align","center"]]],[[["color","#999"]]]],"js":{"functionName":["click"],"functionBlock":["console.log('Header clicked!')"]},"mediaQuery":{"cssClassName":[],"css":[]}},{"parent":"div_0","id":"div_3","tagName":"div","textContent":" ","attachClassName":[],"cssClassName":["footerContainer"],"css":[[[["padding","10px"]],[["width","100%"]],[["height","300px"]],[["bottom","0px"]],[["font-size","64px"]],[["color","#999"]],[["text-align","center"]],[["position","absolute"]],[["border","1px solid #aaa"]]]],"js":{"functionName":[],"functionBlock":[]},"mediaQuery":{"cssClassName":[],"css":[]}},{"parent":"div_3","id":"p_4","tagName":"p","textContent":"footer","attachClassName":[],"cssClassName":[],"css":[],"js":{"functionName":[],"functionBlock":[]},"mediaQuery":{"cssClassName":[],"css":[]}}],"nativeCodeTag":["*"],"nativeCodeCss":[[["margin","0"],["padding","0"],["box-sizing:","border-box"],["-webkit-box-sizing","border-box"]]],"fileName":"pageDemo_3"}